Workbook

Sheet netflix_titles
A1: show_id | B1: type | C1: title | D1: date_added | E1: release_year | F1: rating | G1: monthly_code | H1: duration | I1: duration_type
A2: s1 | B2: Movie | C2: Dick Johnson Is Dead | D2: 44464 | E2: 2020 | F2: PG-13 | G2: =TEXT(IFERROR(DATEVALUE(D2), D2), "mmm") -> Sep | H2: 90 | I2: min
A3: s21 | B3: TV Show | C3: Monsters Inside: The 24 Faces of Billy Milligan | D3: 44461 | E3: 2021 | F3: TV-14 | G3: =TEXT(IFERROR(DATEVALUE(D3), D3), "mmm") -> Sep | H3: 1 | I3: Season
A4: s22 | B4: TV Show | C4: Resurrection: Ertugrul | D4: 44461 | E4: 2018 | F4: TV-14 | G4: =TEXT(IFERROR(DATEVALUE(D4), D4), "mmm") -> Sep | H4: 5 | I4: Seasons
A5: s23 | B5: Movie | C5: Avvai Shanmughi | D5: 44460 | E5: 1996 | F5: TV-PG | G5: =TEXT(IFERROR(DATEVALUE(D5), D5), "mmm") -> Sep | H5: 161 | I5: min
A6: s24 | B6: Movie | C6: Go! Go! Cory Carson: Chrissy Takes the Wheel | D6: 44460 | E6: 2021 | F6: TV-Y | G6: =TEXT(IFERROR(DATEVALUE(D6), D6), "mmm") -> Sep | H6: 61 | I6: min
A7: s25 | B7: Movie | C7: Jeans | D7: 44460 | E7: 1998 | F7: TV-14 | G7: =TEXT(IFERROR(DATEVALUE(D7), D7), "mmm") -> Sep | H7: 166 | I7: min
A8: s26 | B8: TV Show | C8: Love on the Spectrum | D8: 44460 | E8: 2021 | F8: TV-14 | G8: =TEXT(IFERROR(DATEVALUE(D8), D8), "mmm") -> Sep | H8: 2 | I8: Seasons
A9: s27 | B9: Movie | C9: Minsara Kanavu | D9: 44460 | E9: 1997 | F9: TV-PG | G9: =TEXT(IFERROR(DATEVALUE(D9), D9), "mmm") -> Sep | H9: 147 | I9: min
A10: s28 | B10: Movie | C10: Grown Ups | D10: 44459 | E10: 2010 | F10: PG-13 | G10: =TEXT(IFERROR(DATEVALUE(D10), D10), "mmm") -> Sep | H10: 103 | I10: min
A11: s29 | B11: Movie | C11: Dark Skies | D11: 44458 | E11: 2013 | F11: PG-13 | G11: =TEXT(IFERROR(DATEVALUE(D11), D11), "mmm") -> Sep | H11: 97 | I11: min
A12: s30 | B12: Movie | C12: Paranoia | D12: 44458 | E12: 2013 | F12: PG-13 | G12: =TEXT(IFERROR(DATEVALUE(D12), D12), "mmm") -> Sep | H12: 106 | I12: min
A13: s31 | B13: Movie | C13: Ankahi Kahaniya | D13: 44456 | E13: 2021 | F13: TV-14 | G13: =TEXT(IFERROR(DATEVALUE(D13), D13), "mmm") -> Sep | H13: 111 | I13: min
... A840: s858 | B840: TV Show | C840: The Neighbor | D840: 44337 | E840: 2021 | F840: TV-MA | G840: =TEXT(IFERROR(DATEVALUE(D840), D840), "mmm") -> May | H840: 2 | I840: Seasons
A841: s859 | B841: Movie | C841: 678 | D841: 44336 | E841: 2009 | F841: TV-14 | G841: =TEXT(IFERROR(DATEVALUE(D841), D841), "mmm") -> May | H841: 99 | I841: min
A842: s860 | B842: Movie | C842: Asmaa | D842: 44336 | E842: 2011 | F842: TV-14 | G842: =TEXT(IFERROR(DATEVALUE(D842), D842), "mmm") -> May | H842: 92 | I842: min
A843: s861 | B843: Movie | C843: Hating Peter Tatchell | D843: 44336 | E843: 2020 | F843: TV-MA | G843: =TEXT(IFERROR(DATEVALUE(D843), D843), "mmm") -> May | H843: 91 | I843: min
A844: s862 | B844: Movie | C844: Little Singham Future mein Satakli | D844: 44336 | E844: 2021 | F844: TV-Y7 | G844: =TEXT(IFERROR(DATEVALUE(D844), D844), "mmm") -> May | H844: 47 | I844: min
A845: s863 | B845: TV Show | C845: Special | D845: 44336 | E845: 2021 | F845: TV-MA | G845: =TEXT(IFERROR(DATEVALUE(D845), D845), "mmm") -> May | H845: 2 | I845: Seasons
A846: s864 | B846: Movie | C846: Spy Kids: All the Time in the World | D846: 44336 | E846: 2011 | F846: PG | G846: =TEXT(IFERROR(DATEVALUE(D846), D846), "mmm") -> May | H846: 88 | I846: min
A847: s865 | B847: Movie | C847: Taxi No. 9211 | D847: 44336 | E847: 2006 | F847: TV-14 | G847: =TEXT(IFERROR(DATEVALUE(D847), D847), "mmm") -> May | H847: 116 | I847: min
A848: s866 | B848: Movie | C848: Sabotage | D848: 44335 | E848: 2014 | F848: R | G848: =TEXT(IFERROR(DATEVALUE(D848), D848), "mmm") -> May | H848: 109 | I848: min
A849: s867 | B849: Movie | C849: Small Town Crime | D849: 44335 | E849: 2017 | F849: R | G849: =TEXT(IFERROR(DATEVALUE(D849), D849), "mmm") -> May | H849: 92 | I849: min
A850: s868 | B850: Movie | C850: The Last Days | D850: 44335 | E850: 1998 | F850: PG-13 | G850: =TEXT(IFERROR(DATEVALUE(D850), D850), "mmm") -> May | H850: 87 | I850: min
A851: s869 | B851: TV Show | C851: The Magic School Bus | D851: 44335 | E851: 1997 | F851: TV-Y | G851: =TEXT(IFERROR(DATEVALUE(D851), D851), "mmm") -> May | H851: 1 | I851: Season
A852: s870 | B852: TV Show | C852: Who Killed Sara? | D852: 44335 | E852: 2021 | F852: TV-MA | G852: =TEXT(IFERROR(DATEVALUE(D852), D852), "mmm") -> May | H852: 2 | I852: Seasons
A853: s871 | B853: Movie | C853: Amy Tan: Unintended Memoir | D853: 44334 | E853: 2021 | F853: TV-14 | G853: =TEXT(IFERROR(DATEVALUE(D853), D853), "mmm") -> May | H853: 101 | I853: min
... A1095: s1113 | B1095: Movie | C1095: Woody Woodpecker | D1095: 44288 | E1095: 2017 | F1095: PG | G1095: =TEXT(IFERROR(DATEVALUE(D1095), D1095), "mmm") -> Apr | H1095: 91 | I1095: min
A1096: s1114 | B1096: Movie | C1096: 2012 | D1096: 44287 | E1096: 2009 | F1096: PG-13 | G1096: =TEXT(IFERROR(DATEVALUE(D1096), D1096), "mmm") -> Apr | H1096: 158 | I1096: min
A1097: s1115 | B1097: Movie | C1097: 3 Idiots | D1097: 44287 | E1097: 2009 | F1097: PG-13 | G1097: =TEXT(IFERROR(DATEVALUE(D1097), D1097), "mmm") -> Apr | H1097: 164 | I1097: min
A1098: s1116 | B1098: Movie | C1098: Ferrari Ki Sawaari | D1098: 44287 | E1098: 2012 | F1098: TV-PG | G1098: =TEXT(IFERROR(DATEVALUE(D1098), D1098), "mmm") -> Apr | H1098: 133 | I1098: min
A1099: s1117 | B1099: TV Show | C1099: Glimpses of a Future | D1099: 44287 | E1099: 2020 | F1099: TV-PG | G1099: =TEXT(IFERROR(DATEVALUE(D1099), D1099), "mmm") -> Apr | H1099: 1 | I1099: Season
A1100: s1118 | B1100: Movie | C1100: Ibrahim a Fate to Define | D1100: 44287 | E1100: 2019 | F1100: TV-PG | G1100: =TEXT(IFERROR(DATEVALUE(D1100), D1100), "mmm") -> Apr | H1100: 75 | I1100: min
A1101: s1119 | B1101: Movie | C1101: Insidious | D1101: 44287 | E1101: 2010 | F1101: PG-13 | G1101: =TEXT(IFERROR(DATEVALUE(D1101), D1101), "mmm") -> Apr | H1101: 103 | I1101: min
A1102: s1120 | B1102: Movie | C1102: Into the Grizzly Maze | D1102: 44287 | E1102: 2015 | F1102: R | G1102: =TEXT(IFERROR(DATEVALUE(D1102), D1102), "mmm") -> Apr | H1102: 90 | I1102: min
A1103: s1121 | B1103: Movie | C1103: Kingsglaive: Final Fantasy XV | D1103: 44287 | E1103: 2016 | F1103: PG-13 | G1103: =TEXT(IFERROR(DATEVALUE(D1103), D1103), "mmm") -> Apr | H1103: 116 | I1103: min
A1104: s1122 | B1104: Movie | C1104: Legally Blonde | D1104: 44287 | E1104: 2001 | F1104: PG-13 | G1104: =TEXT(IFERROR(DATEVALUE(D1104), D1104), "mmm") -> Apr | H1104: 96 | I1104: min
A1105: s1123 | B1105: Movie | C1105: Madam Chief Minister | D1105: 44287 | E1105: 2020 | F1105: TV-14 | G1105: =TEXT(IFERROR(DATEVALUE(D1105), D1105), "mmm") -> Apr | H1105: 121 | I1105: min
A1106: s1124 | B1106: TV Show | C1106: Magical Andes | D1106: 44287 | E1106: 2021 | F1106: TV-G | G1106: =TEXT(IFERROR(DATEVALUE(D1106), D1106), "mmm") -> Apr | H1106: 2 | I1106: Seasons
A1107: s1125 | B1107: Movie | C1107: Maximum Risk | D1107: 44287 | E1107: 1996 | F1107: R | G1107: =TEXT(IFERROR(DATEVALUE(D1107), D1107), "mmm") -> Apr | H1107: 101 | I1107: min
A1108: s1126 | B1108: TV Show | C1108: Murder Maps | D1108: 44287 | E1108: 2017 | F1108: TV-MA | G1108: =TEXT(IFERROR(DATEVALUE(D1108), D1108), "mmm") -> Apr | H1108: 2 | I1108: Seasons
... A2109: s2127 | B2109: Movie | C2109: What's Your Raashee? | D2109: 44058 | E2109: 2009 | F2109: TV-PG | G2109: =TEXT(IFERROR(DATEVALUE(D2109), D2109), "mmm") -> Aug | H2109: 203 | I2109: min
A2110: s2128 | B2110: TV Show | C2110: 0.03 | D2110: 44057 | E2110: 2020 | F2110: TV-MA | G2110: =TEXT(IFERROR(DATEVALUE(D2110), D2110), "mmm") -> Aug | H2110: 4 | I2110: Seasons
A2111: s2129 | B2111: Movie | C2111: Beyond the Boundary: ICC Women's T20 World Cup Australia 2020 | D2111: 44057 | E2111: 2020 | F2111: TV-G | G2111: =TEXT(IFERROR(DATEVALUE(D2111), D2111), "mmm") -> Aug | H2111: 59 | I2111: min
A2112: s2130 | B2112: Movie | C2112: Fearless | D2112: 44057 | E2112: 2020 | F2112: TV-Y7 | G2112: =TEXT(IFERROR(DATEVALUE(D2112), D2112), "mmm") -> Aug | H2112: 92 | I2112: min
A2113: s2131 | B2113: Movie | C2113: Nigerian Prince | D2113: 44057 | E2113: 2018 | F2113: TV-MA | G2113: =TEXT(IFERROR(DATEVALUE(D2113), D2113), "mmm") -> Aug | H2113: 104 | I2113: min
A2114: s2132 | B2114: Movie | C2114: Octonauts & the Caves of Sac Actun | D2114: 44057 | E2114: 2020 | F2114: TV-Y | G2114: =TEXT(IFERROR(DATEVALUE(D2114), D2114), "mmm") -> Aug | H2114: 72 | I2114: min
A2115: s2133 | B2115: Movie | C2115: Project Power | D2115: 44057 | E2115: 2020 | F2115: R | G2115: =TEXT(IFERROR(DATEVALUE(D2115), D2115), "mmm") -> Aug | H2115: 113 | I2115: min
A2116: s2134 | B2116: TV Show | C2116: Teenage Bounty Hunters | D2116: 44057 | E2116: 2020 | F2116: TV-MA | G2116: =TEXT(IFERROR(DATEVALUE(D2116), D2116), "mmm") -> Aug | H2116: 1 | I2116: Season
A2117: s2135 | B2117: TV Show | C2117: The Great Heist | D2117: 44057 | E2117: 2020 | F2117: TV-MA | G2117: =TEXT(IFERROR(DATEVALUE(D2117), D2117), "mmm") -> Aug | H2117: 1 | I2117: Season
A2118: s2136 | B2118: TV Show | C2118: The Legend of Korra | D2118: 44057 | E2118: 2014 | F2118: TV-Y7 | G2118: =TEXT(IFERROR(DATEVALUE(D2118), D2118), "mmm") -> Aug | H2118: 4 | I2118: Seasons
A2119: s2137 | B2119: TV Show | C2119: Zoids Wild | D2119: 44057 | E2119: 2018 | F2119: TV-Y7 | G2119: =TEXT(IFERROR(DATEVALUE(D2119), D2119), "mmm") -> Aug | H2119: 1 | I2119: Season
A2120: s2138 | B2120: Movie | C2120: An Easy Girl | D2120: 44056 | E2120: 2019 | F2120: TV-MA | G2120: =TEXT(IFERROR(DATEVALUE(D2120), D2120), "mmm") -> Aug | H2120: 93 | I2120: min
A2121: s2139 | B2121: Movie | C2121: Christine | D2121: 44056 | E2121: 2016 | F2121: R | G2121: =TEXT(IFERROR(DATEVALUE(D2121), D2121), "mmm") -> Aug | H2121: 119 | I2121: min
A2122: s2140 | B2122: Movie | C2122: Simon Killer | D2122: 44056 | E2122: 2012 | F2122: TV-MA | G2122: =TEXT(IFERROR(DATEVALUE(D2122), D2122), "mmm") -> Aug | H2122: 105 | I2122: min
... A2425: s2443 | B2425: Movie | C2425: X Large | D2425: 43984 | E2425: 2011 | F2425: TV-14 | G2425: =TEXT(IFERROR(DATEVALUE(D2425), D2425), "mmm") -> Jun | H2425: 135 | I2425: min
A2426: s2444 | B2426: Movie | C2426: 122 | D2426: 43983 | E2426: 2019 | F2426: TV-MA | G2426: =TEXT(IFERROR(DATEVALUE(D2426), D2426), "mmm") -> Jun | H2426: 95 | I2426: min
A2427: s2445 | B2427: TV Show | C2427: Cardcaptor Sakura | D2427: 43983 | E2427: 1999 | F2427: TV-Y7 | G2427: =TEXT(IFERROR(DATEVALUE(D2427), D2427), "mmm") -> Jun | H2427: 2 | I2427: Seasons
A2428: s2446 | B2428: Movie | C2428: Chippa | D2428: 43983 | E2428: 2020 | F2428: TV-14 | G2428: =TEXT(IFERROR(DATEVALUE(D2428), D2428), "mmm") -> Jun | H2428: 92 | I2428: min
A2429: s2447 | B2429: Movie | C2429: Cook Off | D2429: 43983 | E2429: 2017 | F2429: TV-G | G2429: =TEXT(IFERROR(DATEVALUE(D2429), D2429), "mmm") -> Jun | H2429: 100 | I2429: min
A2430: s2448 | B2430: TV Show | C2430: Dear My Friends | D2430: 43983 | E2430: 2016 | F2430: TV-MA | G2430: =TEXT(IFERROR(DATEVALUE(D2430), D2430), "mmm") -> Jun | H2430: 1 | I2430: Season
A2431: s2449 | B2431: Movie | C2431: Kalek Shanab | D2431: 43983 | E2431: 2019 | F2431: TV-PG | G2431: =TEXT(IFERROR(DATEVALUE(D2431), D2431), "mmm") -> Jun | H2431: 80 | I2431: min
A2432: s2450 | B2432: TV Show | C2432: Megalobox | D2432: 43983 | E2432: 2018 | F2432: TV-MA | G2432: =TEXT(IFERROR(DATEVALUE(D2432), D2432), "mmm") -> Jun | H2432: 1 | I2432: Season
A2433: s2451 | B2433: TV Show | C2433: Midnight Diner | D2433: 43983 | E2433: 2014 | F2433: TV-MA | G2433: =TEXT(IFERROR(DATEVALUE(D2433), D2433), "mmm") -> Jun | H2433: 3 | I2433: Seasons
A2434: s2452 | B2434: Movie | C2434: Mirai | D2434: 43983 | E2434: 2018 | F2434: PG | G2434: =TEXT(IFERROR(DATEVALUE(D2434), D2434), "mmm") -> Jun | H2434: 98 | I2434: min
A2435: s2453 | B2435: TV Show | C2435: My Shy Boss | D2435: 43983 | E2435: 2017 | F2435: TV-MA | G2435: =TEXT(IFERROR(DATEVALUE(D2435), D2435), "mmm") -> Jun | H2435: 1 | I2435: Season
A2436: s2454 | B2436: TV Show | C2436: Revolutionary Love | D2436: 43983 | E2436: 2017 | F2436: TV-MA | G2436: =TEXT(IFERROR(DATEVALUE(D2436), D2436), "mmm") -> Jun | H2436: 1 | I2436: Season
A2437: s2455 | B2437: Movie | C2437: The Disaster Artist | D2437: 43983 | E2437: 2017 | F2437: R | G2437: =TEXT(IFERROR(DATEVALUE(D2437), D2437), "mmm") -> Jun | H2437: 104 | I2437: min
A2438: s2456 | B2438: Movie | C2438: The Stolen | D2438: 43983 | E2438: 2016 | F2438: TV-14 | G2438: =TEXT(IFERROR(DATEVALUE(D2438), D2438), "mmm") -> Jun | H2438: 98 | I2438: min
... A2780: s2798 | B2780: TV Show | C2780: Vampires | D2780: 43910 | E2780: 2020 | F2780: TV-MA | G2780: =TEXT(IFERROR(DATEVALUE(D2780), D2780), "mmm") -> Mar | H2780: 1 | I2780: Season
A2781: s2799 | B2781: Movie | C2781: 3022 | D2781: 43909 | E2781: 2019 | F2781: R | G2781: =TEXT(IFERROR(DATEVALUE(D2781), D2781), "mmm") -> Mar | H2781: 91 | I2781: min
A2782: s2800 | B2782: Movie | C2782: Altered Carbon: Resleeved | D2782: 43909 | E2782: 2020 | F2782: TV-MA | G2782: =TEXT(IFERROR(DATEVALUE(D2782), D2782), "mmm") -> Mar | H2782: 75 | I2782: min
A2783: s2801 | B2783: Movie | C2783: Masameer - The Movie | D2783: 43909 | E2783: 2020 | F2783: TV-14 | G2783: =TEXT(IFERROR(DATEVALUE(D2783), D2783), "mmm") -> Mar | H2783: 100 | I2783: min
A2784: s2802 | B2784: Movie | C2784: AllI Wish | D2784: 43908 | E2784: 2017 | F2784: R | G2784: =TEXT(IFERROR(DATEVALUE(D2784), D2784), "mmm") -> Mar | H2784: 95 | I2784: min
A2785: s2803 | B2785: TV Show | C2785: Caliphate | D2785: 43908 | E2785: 2020 | F2785: TV-MA | G2785: =TEXT(IFERROR(DATEVALUE(D2785), D2785), "mmm") -> Mar | H2785: 1 | I2785: Season
A2786: s2804 | B2786: Movie | C2786: Lu Over the Wall | D2786: 43908 | E2786: 2017 | F2786: PG | G2786: =TEXT(IFERROR(DATEVALUE(D2786), D2786), "mmm") -> Mar | H2786: 113 | I2786: min
A2787: s2805 | B2787: TV Show | C2787: Women Of The Night | D2787: 43908 | E2787: 2019 | F2787: TV-MA | G2787: =TEXT(IFERROR(DATEVALUE(D2787), D2787), "mmm") -> Mar | H2787: 1 | I2787: Season
A2788: s2806 | B2788: Movie | C2788: XV: Beyond the Tryline | D2788: 43908 | E2788: 2016 | F2788: TV-14 | G2788: =TEXT(IFERROR(DATEVALUE(D2788), D2788), "mmm") -> Mar | H2788: 91 | I2788: min
A2789: s2807 | B2789: Movie | C2789: Bert Kreischer: Hey Big Boy | D2789: 43907 | E2789: 2020 | F2789: TV-MA | G2789: =TEXT(IFERROR(DATEVALUE(D2789), D2789), "mmm") -> Mar | H2789: 62 | I2789: min
A2790: s2808 | B2790: TV Show | C2790: Shaun the Sheep: Adventures from Mossy Bottom | D2790: 43907 | E2790: 2020 | F2790: TV-Y7 | G2790: =TEXT(IFERROR(DATEVALUE(D2790), D2790), "mmm") -> Mar | H2790: 1 | I2790: Season
A2791: s2809 | B2791: TV Show | C2791: We Speak Dance | D2791: 43907 | E2791: 2018 | F2791: TV-MA | G2791: =TEXT(IFERROR(DATEVALUE(D2791), D2791), "mmm") -> Mar | H2791: 1 | I2791: Season
A2792: s2810 | B2792: Movie | C2792: Search Party | D2792: 43906 | E2792: 2014 | F2792: R | G2792: =TEXT(IFERROR(DATEVALUE(D2792), D2792), "mmm") -> Mar | H2792: 93 | I2792: min
A2793: s2811 | B2793: Movie | C2793: Bypass Road | D2793: 43905 | E2793: 2019 | F2793: TV-14 | G2793: =TEXT(IFERROR(DATEVALUE(D2793), D2793), "mmm") -> Mar | H2793: 135 | I2793: min
... A3790: s3808 | B3790: TV Show | C3790: Rosario Tijeras | D3790: 43605 | E3790: 2018 | F3790: TV-MA | G3790: =TEXT(IFERROR(DATEVALUE(D3790), D3790), "mmm") -> May | H3790: 2 | I3790: Seasons
A3791: s3809 | B3791: TV Show | C3791: 1994 | D3791: 43602 | E3791: 2019 | F3791: TV-MA | G3791: =TEXT(IFERROR(DATEVALUE(D3791), D3791), "mmm") -> May | H3791: 1 | I3791: Season
A3792: s3810 | B3792: Movie | C3792: Born in Gaza | D3792: 43602 | E3792: 2014 | F3792: TV-14 | G3792: =TEXT(IFERROR(DATEVALUE(D3792), D3792), "mmm") -> May | H3792: 70 | I3792: min
A3793: s3811 | B3793: Movie | C3793: Born in Syria | D3793: 43602 | E3793: 2016 | F3793: TV-14 | G3793: =TEXT(IFERROR(DATEVALUE(D3793), D3793), "mmm") -> May | H3793: 87 | I3793: min
A3794: s3812 | B3794: Movie | C3794: Dying to Tell | D3794: 43602 | E3794: 2018 | F3794: TV-MA | G3794: =TEXT(IFERROR(DATEVALUE(D3794), D3794), "mmm") -> May | H3794: 88 | I3794: min
A3795: s3813 | B3795: TV Show | C3795: It's Bruno! | D3795: 43602 | E3795: 2019 | F3795: TV-MA | G3795: =TEXT(IFERROR(DATEVALUE(D3795), D3795), "mmm") -> May | H3795: 1 | I3795: Season
A3796: s3814 | B3796: Movie | C3796: Maria | D3796: 43602 | E3796: 2019 | F3796: TV-MA | G3796: =TEXT(IFERROR(DATEVALUE(D3796), D3796), "mmm") -> May | H3796: 90 | I3796: min
A3797: s3815 | B3797: Movie | C3797: ReMastered: The Lion's Share | D3797: 43602 | E3797: 2019 | F3797: TV-14 | G3797: =TEXT(IFERROR(DATEVALUE(D3797), D3797), "mmm") -> May | H3797: 84 | I3797: min
A3798: s3816 | B3798: Movie | C3798: Saverio Raimondo: Il Satiro Parlante | D3798: 43602 | E3798: 2019 | F3798: TV-MA | G3798: =TEXT(IFERROR(DATEVALUE(D3798), D3798), "mmm") -> May | H3798: 53 | I3798: min
A3799: s3817 | B3799: Movie | C3799: See You Yesterday | D3799: 43602 | E3799: 2019 | F3799: TV-MA | G3799: =TEXT(IFERROR(DATEVALUE(D3799), D3799), "mmm") -> May | H3799: 87 | I3799: min
A3800: s3818 | B3800: TV Show | C3800: White Gold | D3800: 43602 | E3800: 2019 | F3800: TV-MA | G3800: =TEXT(IFERROR(DATEVALUE(D3800), D3800), "mmm") -> May | H3800: 2 | I3800: Seasons
A3801: s3819 | B3801: Movie | C3801: Good Sam | D3801: 43601 | E3801: 2019 | F3801: TV-PG | G3801: =TEXT(IFERROR(DATEVALUE(D3801), D3801), "mmm") -> May | H3801: 90 | I3801: min
A3802: s3820 | B3802: Movie | C3802: Jonaki | D3802: 43601 | E3802: 2018 | F3802: TV-MA | G3802: =TEXT(IFERROR(DATEVALUE(D3802), D3802), "mmm") -> May | H3802: 96 | I3802: min
A3803: s3821 | B3803: Movie | C3803: PATRICK (2019) | D3803: 43601 | E3803: 2019 | F3803: TV-PG | G3803: =TEXT(IFERROR(DATEVALUE(D3803), D3803), "mmm") -> May | H3803: 94 | I3803: min
... A3944: s3962 | B3944: TV Show | C3944: Pablo | D3944: 43554 | E3944: 2017 | F3944: TV-Y | G3944: =TEXT(IFERROR(DATEVALUE(D3944), D3944), "mmm") -> Mar | H3944: 1 | I3944: Season
A3945: s3963 | B3945: Movie | C3945: 46249 | D3945: 43553 | E3945: 2019 | F3945: TV-14 | G3945: =TEXT(IFERROR(DATEVALUE(D3945), D3945), "mmm") -> Mar | H3945: 124 | I3945: min
A3946: s3964 | B3946: Movie | C3946: Bayonet | D3946: 43553 | E3946: 2019 | F3946: TV-MA | G3946: =TEXT(IFERROR(DATEVALUE(D3946), D3946), "mmm") -> Mar | H3946: 102 | I3946: min
...

Sheet Question & Answer
A1: Practical Exercise
K2: EX1 | N2: EX3 | Q2: EX4 | S2: EX5
A3: 1). Display a count of movies by film duration in a pivot table, sorted by count of movie | K3: type | L3: Movie | N3: type | O3: TV Show | Q3: Release Year | S3: Sum of duration | T3: Column Labels
A4: Ans | Q4: {=_xlfn._xlws.SORT(_xlfn.UNIQUE(netflix_titles!E:E))} -> 1925 | S4: Row Labels | T4: 66 min | U4: 74 min | V4: 84 min | W4: G | X4: NC-17 | Y4: NR | Z4: PG | AA4: PG-13 | AB4: R | AC4: TV-14 | AD4: TV-G | AE4: TV-MA | AF4: TV-PG | AG4: TV-Y | AH4: TV-Y7 | AI4: TV-Y7-FV | AJ4: UR | AK4: (blank) | AL4: Grand Total
K5: Row Labels | L5: Count of Movie | N5: Row Labels | O5: Count of show_id | Q5: 1942 | S5: 1925 | AC5: 1 | AL5: 1
K6: 90 min | L6: 152 | N6: Jan | O6: 202 | Q6: 1943 | S6: 1942 | AC6: 70 | AL6: 70
A7: 2). Sum the duration of movies released between 1990 and 2000 using sumifs. | K7: 93 min | L7: 146 | N7: Feb | O7: 181 | Q7: 1944 | S7: 1943 | AF7: 188 | AL7: 188
A8: Ans | B8: =SUMIFS(netflix_titles!H:H,netflix_titles!E:E,">1990",netflix_titles!E:E,"<2000",netflix_titles!B:B,"Movie") -> 25095 | K8: 94 min | L8: 146 | N8: Mar | O8: 213 | Q8: 1945 | S8: 1944 | AC8: 116 | AF8: 40 | AL8: 156
K9: 97 min | L9: 146 | N9: Apr | O9: 214 | Q9: 1946 | S9: 1945 | AC9: 95 | AE9: 60 | AL9: 155
K10: 91 min | L10: 144 | N10: May | O10: 193 | Q10: 1947 | S10: 1946 | AC10: 1 | AF10: 58 | AL10: 59
A11: 3). Count how many TV shows were added each month, regardless of the year. | K11: 95 min | L11: 137 | N11: Jun | O11: 236 | Q11: 1954 | S11: 1947 | AF11: 42 | AL11: 42
A12: Ans | K12: 96 min | L12: 130 | N12: Jul | O12: 262 | Q12: 1955 | S12: 1954 | AC12: 116 | AD12: 120 | AL12: 236
K13: 92 min | L13: 129 | N13: Aug | O13: 236 | Q13: 1956 | S13: 1955 | AA13: 111 | AC13: 97 | AF13: 93 | AL13: 301
K14: 102 min | L14: 122 | N14: Sep | O14: 239 | Q14: 1958 | S14: 1956 | W14: 98 | AC14: 104 | AL14: 202
A15: 4). Display a unique list of release years. | K15: 98 min | L15: 120 | N15: Oct | O15: 215 | Q15: 1959 | S15: 1958 | W15: 115 | Y15: 108 | AC15: 73 | AL15: 296
A16: Ans | K16: 99 min | L16: 118 | N16: Nov | O16: 207 | Q16: 1960 | S16: 1959 | AC16: 143 | AL16: 143
K17: 88 min | L17: 116 | N17: Dec | O17: 266 | Q17: 1961 | S17: 1960 | AC17: 289 | AF17: 285 | AL17: 574
K18: 101 min | L18: 116 | N18: Grand Total | O18: 2664 | Q18: 1962 | S18: 1961 | AC18: 156 | AL18: 156
A19: 5). Show a pivot table by rating on columns, Release year on rows, sum of duration as value. | K19: 103 min | L19: 114 | Q19: 1963 | S19: 1962 | AB19: 153 | AF19: 348 | AL19: 501
A20: Ans | K20: 106 min | L20: 111 | Q20: 1964 | S20: 1963 | AC20: 4 | AE20: 194 | AL20: 198
K21: 100 min | L21: 108 | Q21: 1965 | S21: 1964 | W21: 173 | AC21: 228 | AL21: 401
K22: 89 min | L22: 106 | Q22: 1966 | S22: 1965 | AA22: 200 | AC22: 103 | AL22: 303
A23: 6). Show the title follwing the idusing xlookup | K23: 104 min | L23: 104 | Q23: 1967 | S23: 1966 | AF23: 116 | AL23: 116
A24: s100 | B24: =_xlfn.XLOOKUP('Question & Answer'!A24,netflix_titles!A:A,netflix_titles!C:C) -> On the Verge | K24: 86 min | L24: 103 | Q24: 1968 | S24: 1967 | AB24: 201 | AC24: 127 | AD24: 8 | AE24: 93 | AL24: 429
A25: s2880 | B25: =_xlfn.XLOOKUP('Question & Answer'!A25,netflix_titles!A:A,netflix_titles!C:C) -> Gbomo Gbomo Express | K25: 105 min | L25: 101 | Q25: 1969 | S25: 1968 | W25: 146 | AA25: 166 | AB25: 137 | AL25: 449
A26: s3330 | B26: =_xlfn.XLOOKUP('Question & Answer'!A26,netflix_titles!A:A,netflix_titles!C:C) -> American Son | K26: 87 min | L26: 101 | Q26: 1970 | S26: 1969 | W26: 128 | AF26: 152 | AL26: 280
K27: 107 min | L27: 98 | Q27: 1971 | S27: 1970 | AE27: 130 | AF27: 66 | AL27: 196
K28: 110 min | L28: 97 | Q28: 1972 | S28: 1971 | W28: 281 | AB28: 137 | AC28: 296 | AL28: 714
K29: 108 min | L29: 87 | Q29: 1973 | S29: 1972 | AB29: 91 | AC29: 115 | AE29: 105 | AF29: 125 | AL29: 436
K30: 116 min | L30: 80 | Q30: 1974 | S30: 1973 | W30: 94 | Y30: 81 | Z30: 89 | AB30: 317 | AC30: 553 | AE30: 97 | AL30: 1231
K31: 112 min | L31: 74 | Q31: 1975 | S31: 1974 | Z31: 112 | AB31: 204 | AC31: 166 | AF31: 104 | AJ31: 103 | AL31: 689
K32: 85 min | L32: 73 | Q32: 1976 | S32: 1975 | Z32: 216 | AC32: 240 | AE32: 197 | AF32: 127 | AL32: 780
K33: 109 min | L33: 69 | Q33: 1977 | S33: 1976 | Z33: 472 | AB33: 98 | AC33: 156 | AE33: 124 | AF33: 292 | AL33: 1142
K34: 113 min | L34: 69 | Q34: 1978 | S34: 1977 | W34: 84 | Z34: 272 | AC34: 172 | AE34: 150 | AF34: 133 | AL34: 811
K35: 111 min | L35: 68 | Q35: 1979 | S35: 1978 | Z35: 226 | AB35: 97 | AD35: 25 | AE35: 172 | AF35: 141 | AL35: 661
K36: 84 min | L36: 67 | Q36: 1980 | S36: 1979 | Z36: 119 | AA36: 100 | AB36: 187 | AC36: 472 | AE36: 210 | AF36: 138 | AL36: 1226
K37: 118 min | L37: 65 | Q37: 1981 | S37: 1980 | Z37: 114 | AB37: 532 | AC37: 550 | AF37: 120 | AL37: 1316
K38: 83 min | L38: 65 | Q38: 1982 | S38: 1981 | Y38: 86 | Z38: 224 | AB38: 209 | AC38: 817 | AE38: 85 | AF38: 92 | AH38: 1 | AL38: 1514
K39: 119 min | L39: 63 | Q39: 1983 | S39: 1982 | Z39: 193 | AB39: 301 | AC39: 988 | AE39: 269 | AF39: 373 | AL39: 2124
K40: 81 min | L40: 62 | Q40: 1984 | S40: 1983 | Z40: 98 | AC40: 710 | AE40: 406 | AL40: 1214
K41: 115 min | L41: 61 | Q41: 1985 | S41: 1984 | Z41: 478 | AA41: 114 | AB41: 229 | AC41: 739 | AE41: 86 | AL41: 1646
K42: 117 min | L42: 61 | Q42: 1986 | S42: 1985 | Y42: 95 | Z42: 92 | AC42: 660 | AE42: 186 | AL42: 1033
K43: 120 min | L43: 56 | Q43: 1987 | S43: 1986 | W43: 80 | Z43: 214 | AA43: 197 | AB43: 210 | AC43: 416 | AE43: 96 | AL43: 1213
K44: 114 min | L44: 56 | Q44: 1988 | S44: 1987 | Y44: 84 | AA44: 200 | AB44: 200 | AC44: 172 | AE44: 50 | AF44: 96 | AL44: 802
K45: 121 min | L45: 54 | Q45: 1989 | S45: 1988 | AA45: 260 | AB45: 571 | AC45: 363 | AE45: 94 | AF45: 387 | AL45: 1675
K46: 124 min | L46: 52 | Q46: 1990 | S46: 1989 | W46: 85 | Z46: 331 | AA46: 224 | AB46: 120 | AC46: 422 | AE46: 190 | AF46: 286 | AH46: 1 | AL46: 1659
K47: 82 min | L47: 52 | Q47: 1991 | S47: 1990 | Z47: 94 | AA47: 501 | AB47: 440 | AC47: 898 | AE47: 286 | AF47: 5 | AL47: 2224
K48: 127 min | L48: 48 | Q48: 1992 | S48: 1991 | W48: 75 | Y48: 206 | Z48: 88 | AA48: 187 | AB48: 199 | AC48: 256 | AD48: 1 | AE48: 272 | AF48: 93 | AL48: 1377
K49: 78 min | L49: 45 | Q49: 1993 | S49: 1992 | Z49: 325 | AA49: 73 | AB49: 1129 | AC49: 259 | AE49: 294 | AF49: 15 | AG49: 10 | AL49: 2105
K50: 122 min | L50: 45 | Q50: 1994 | S50: 1993 | Z50: 406 | AA50: 467 | AB50: 766 | AC50: 763 | AD50: 1 | AE50: 181 | AF50: 98 | AH50: 1 | AL50: 2683
K51: 123 min | L51: 44 | Q51: 1995 | S51: 1994 | Z51: 297 | AA51: 565 | AB51: 468 | AC51: 1018 | AD51: 1 | AE51: 63 | AF51: 58 | AL51: 2470
K52: 126 min | L52: 44 | Q52: 1996 | S52: 1995 | W52: 78 | Z52: 197 | AA52: 1089 | AB52: 409 | AC52: 510 | AD52: 2 | AE52: 1 | AF52: 339 | AL52: 2625
K53: 80 min | L53: 43 | Q53: 1997 | S53: 1996 | Z53: 103 | AA53: 626 | AB53: 1014 | AC53: 692 | AF53: 162 | AH53: 2 | AL53: 2599
K54: 133 min | L54: 42 | Q54: 1998 | S54: 1997 | Z54: 96 | AA54: 977 | AB54: 1870 | AC54: 560 | AD54: 3 | AE54: 337 | AF54: 147 | AG54: 1 | AH54: 1 | AL54: 3992
K55: 128 min | L55: 41 | Q55: 1999 | S55: 1998 | W55: 81 | AA55: 722 | AB55: 997 | AC55: 1070 | AD55: 5 | AE55: 541 | AF55: 83 | AH55: 1 | AL55: 3500
K56: 130 min | L56: 40 | Q56: 2000 | S56: 1999 | W56: 164 | Z56: 201 | AA56: 831 | AB56: 1210 | AC56: 315 | AD56: 352 | AE56: 432 | AF56: 328 | AH56: 3 | AL56: 3836
K57: 135 min | L57: 39 | Q57: 2001 | S57: 2000 | W57: 158 | Z57: 369 | AA57: 1102 | AB57: 842 | AC57: 777 | AE57: 56 | AF57: 374 | AH57: 2 | AL57: 3680
K58: 137 min | L58: 38 | Q58: 2002 | S58: 2001 | W58: 158 | Z58: 606 | AA58: 859 | AB58: 1618 | AC58: 970 | AD58: 1 | AE58: 208 | AF58: 142 | AH58: 61 | AL58: 4623
K59: 132 min | L59: 37 | Q59: 2003 | S59: 2002 | Z59: 368 | AA59: 1634 | AB59: 1343 | AC59: 1083 | AE59: 700 | AF59: 149 | AH59: 1 | AL59: 5278
K60: 125 min | L60: 36 | Q60: 2004 | S60: 2003 | Z60: 450 | AA60: 1213 | AB60: 1875 | AC60: 1398 | AE60: 849 | AF60: 145 | AG60: 37 | AH60: 3 | AL60: 5970
K61: 75 min | L61: 35 | Q61: 2005 | S61: 2004 | W61: 225 | Y61: 107 | Z61: 852 | AA61: 822 | AB61: 741 | AC61: 1508 | AE61: 883 | AF61: 1161 | AG61: 1 | AH61: 1 | AL61: 6301
K62: 79 min | L62: 35 | Q62: 2006 | S62: 2005 | W62: 154 | Z62: 490 | AA62: 1706 | AB62: 1122 | AC62: 2559 | AE62: 561 | AF62: 1068 | AH62: 5 | AL62: 7665
K63: 131 min | L63: 34 | Q63: 2007 | S63: 2006 | Y63: 85 | Z63: 727 | AA63: 1744 | AB63: 1331 | AC63: 3144 | AE63: 1307 | AF63: 848 | AH63: 128 | AL63: 9314
K64: 72 min | L64: 33 | Q64: 2008 | S64: 2007 | W64: 89 | Y64: 161 | Z64: 1072 | AA64: 1683 | AB64: 1652 | AC64: 1821 | AE64: 1196 | AF64: 653 | AG64: 79 | AH64: 8 | AL64: 8414
K65: 129 min | L65: 32 | Q65: 2009 | S65: 2008 | Z65: 943 | AA65: 2500 | AB65: 2072 | AC65: 3534 | AD65: 111 | AE65: 1990 | AF65: 635 | AG65: 26 | AH65: 111 | AJ65: 113 | AL65: 12035
K66: 63 min | L66: 32 | Q66: 2010 | S66: 2009 | W66: 353 | Z66: 977 | AA66: 2932 | AB66: 2596 | AC66: 3841 | AD66: 1 | AE66: 757 | AF66: 1244 | AH66: 196 | AL66: 12897
K67: 74 min | L67: 31 | Q67: 2011 | S67: 2010 | Y67: 427 | Z67: 783 | AA67: 2892 | AB67: 2819 | AC67: 3858 | AD67: 246 | AE67: 3501 | AF67: 983 | AG67: 167 | AH67: 372 | AL67: 16048
K68: 76 min | L68: 31 | Q68: 2012 | S68: 2011 | W68: 106 | Y68: 134 | Z68: 1750 | AA68: 2507 | AB68: 2034 | AC68: 4418 | AD68: 93 | AE68: 2187 | AF68: 1126 | AG68: 184 | AH68: 431 | AL68: 14970
K69: 61 min | L69: 31 | Q69: 2013 | S69: 2012 | Y69: 438 | Z69: 669 | AA69: 2071 | AB69: 3113 | AC69: 5322 | AD69: 145 | AE69: 3864 | AF69: 1113 | AG69: 177 | AH69: 594 | AI69: 43 | AL69: 17549
K70: 77 min | L70: 30 | Q70: 2014 | S70: 2013 | X70: 180 | Y70: 554 | Z70: 1315 | AA70: 1610 | AB70: 4244 | AC70: 5930 | AD70: 354 | AE70: 4830 | AF70: 1859 | AG70: 314 | AH70: 896 | AI70: 78 | AK70: 1 | AL70: 22165
K71: 73 min | L71: 30 | Q71: 2015 | S71: 2014 | W71: 156 | X71: 112 | Y71: 655 | Z71: 1449 | AA71: 2061 | AB71: 5074 | AC71: 7459 | AD71: 248 | AE71: 6137 | AF71: 2404 | AG71: 269 | AH71: 581 | AI71: 2 | AL71: 26607
K72: 60 min | L72: 29 | Q72: 2016 | S72: 2015 | Y72: 1617 | Z72: 1051 | AA72: 2529 | AB72: 6821 | AC72: 9637 | AD72: 361 | AE72: 13085 | AF72: 3719 | AG72: 602 | AH72: 249 | AK72: 116 | AL72: 39787
K73: 66 min | L73: 28 | Q73: 2017 | S73: 2016 | W73: 269 | Y73: 1950 | Z73: 1346 | AA73: 3439 | AB73: 8768 | AC73: 14458 | AD73: 1004 | AE73: 25597 | AF73: 4769 | AG73: 549 | AH73: 737 | AI73: 153 | AJ73: 103 | AL73: 63142
K74: 69 min | L74: 28 | Q74: 2018 | S74: 2017 | W74: 78 | Y74: 235 | Z74: 1366 | AA74: 3403 | AB74: 7250 | AC74: 19198 | AD74: 1693 | AE74: 31918 | AF74: 7086 | AG74: 715 | AH74: 675 | AK74: 37 | AL74: 73654
K75: 71 min | L75: 28 | Q75: 2019 | S75: 2018 | W75: 177 | X75: 83 | Y75: 86 | Z75: 3053 | AA75: 3314 | AB75: 5467 | AC75: 17664 | AD75: 1402 | AE75: 35106 | AF75: 6336 | AG75: 663 | AH75: 995 | AI75: 68 | AL75: 74414
K76: 70 min | L76: 28 | Q76: 2020 | S76: 2019 | W76: 87 | Z76: 1125 | AA76: 1911 | AB76: 4299 | AC76: 17069 | AD76: 1110 | AE76: 27008 | AF76: 5070 | AG76: 1135 | AH76: 1092 | AL76: 59906
K77: 65 min | L77: 25 | Q77: 2021 | S77: 2020 | W77: 9 | Z77: 1356 | AA77: 2136 | AB77: 5146 | AC77: 9697 | AD77: 2082 | AE77: 21370 | AF77: 3852 | AG77: 1356 | AH77: 1310 | AL77: 48314
K78: 58 min | L78: 25 | Q78: release_year | S78: 2021 | Z78: 942 | AA78: 1300 | AB78: 2335 | AC78: 7201 | AD78: 843 | AE78: 10808 | AF78: 1802 | AG78: 344 | AH78: 1150 | AL78: 26725
K79: 68 min | L79: 25 | Q79: 0 | S79: Grand Total | W79: 3701 | X79: 375 | Y79: 7109 | Z79: 28116 | AA79: 52978 | AB79: 85058 | AC79: 158617 | AD79: 10212 | AE79: 199319 | AF79: 51668 | AG79: 6629 | AH79: 9608 | AI79: 344 | AJ79: 319 | AK79: 154 | AL79: 614207
K80: 140 min | L80: 25
K81: 59 min | L81: 25
K82: 53 min | L82: 24
K83: 62 min | L83: 24
K84: 46 min | L84: 24
K85: 54 min | L85: 24
K86: 24 min | L86: 23
K87: 136 min | L87: 23
K88: 143 min | L88: 23
K89: 64 min | L89: 23
K90: 134 min | L90: 22
K91: 139 min | L91: 22
... K212: Grand Total | L212: 6131

Sheet cast
A1: show_id | B1: cast_1 | C1: cast_2 | D1: cast_3 | E1: cast_4 | F1: cast_5 | G1: cast_6 | H1: cast_7 | I1: cast_8 | J1: cast_9 | K1: cast_10 | L1: cast_11 | M1: cast_12 | N1: cast_13 | O1: cast_14 | P1: cast_15 | Q1: cast_16 | R1: cast_17 | S1: cast_18 | T1: cast_19 | U1: cast_20 | V1: cast_21 | W1: cast_22 | X1: cast_23 | Y1: cast_24 | Z1: cast_25 | AA1: cast_26 | AB1: cast_27 | AC1: cast_28 | AD1: cast_29 | AE1: cast_30 | AF1: cast_31 | AG1: cast_32 | AH1: cast_33 | AI1: cast_34 | AJ1: cast_35 | AK1: cast_36 | AL1: cast_37 | AM1: cast_38 | AN1: cast_39 | AO1: cast_40 | AP1: cast_41 | AQ1: cast_42 | AR1: cast_43 | AS1: cast_44 | AT1: cast_45 | AU1: cast_46 | AV1: cast_47 | AW1: cast_48 | AX1: cast_49 | AY1: cast_50
A2: s1
A3: s2 | B3: Ama Qamata | C3: Khosi Ngema | D3: Gail Mabalane | E3: Thabang Molaba | F3: Dillon Windvogel | G3: Natasha Thahane | H3: Arno Greeff | I3: Xolile Tshabalala | J3: Getmore Sithole | K3: Cindy Mahlangu | L3: Ryle De Morny | M3: Greteli Fincham | N3: Sello Maake Ka-Ncube | O3: Odwa Gwanya | P3: Mekaila Mathys | Q3: Sandi Schultz | R3: Duane Williams | S3: Shamilla Miller | T3: Patrick Mofokeng
A4: s3 | B4: Sami Bouajila | C4: Tracy Gotoas | D4: Samuel Jouy | E4: Nabiha Akkari | F4: Sofia Lesaffre | G4: Salim Kechiouche | H4: Noureddine Farihi | I4: Geert Van Rampelberg | J4: Bakary Diombera
A5: s4
A6: s5 | B6: Mayur More | C6: Jitendra Kumar | D6: Ranjan Raj | E6: Alam Khan | F6: Ahsaas Channa | G6: Revathi Pillai | H6: Urvi Singh | I6: Arun Kumar
A7: s6 | B7: Kate Siegel | C7: Zach Gilford | D7: Hamish Linklater | E7: Henry Thomas | F7: Kristin Lehman | G7: Samantha Sloyan | H7: Igby Rigney | I7: Rahul Kohli | J7: Annarah Cymone | K7: Annabeth Gish | L7: Alex Essoe | M7: Rahul Abburi | N7: Matt Biedel | O7: Michael Trucco | P7: Crystal Balint | Q7: Louis Oliver
A8: s7 | B8: Vanessa Hudgens | C8: Kimiko Glenn | D8: James Marsden | E8: Sofia Carson | F8: Liza Koshy | G8: Ken Jeong | H8: Elizabeth Perkins | I8: Jane Krakowski | J8: Michael McKean | K8: Phil LaMarr
A9: s8 | B9: Kofi Ghanaba | C9: Oyafunmike Ogunlano | D9: Alexandra Duah | E9: Nick Medley | F9: Mutabaruka | G9: Afemo Omilami | H9: Reggie Carter | I9: Mzuri
A10: s9 | B10: Mel Giedroyc | C10: Sue Perkins | D10: Mary Berry | E10: Paul Hollywood
A11: s10 | B11: Melissa McCarthy | C11: Chris O'Dowd | D11: Kevin Kline | E11: Timothy Olyphant | F11: Daveed Diggs | G11: Skyler Gisondo | H11: Laura Harrier | I11: Rosalind Chao | J11: Kimberly Quinn | K11: Loretta Devine | L11: Ravi Kapoor
A12: s11
A13: s12 | B13: Sukollawat Kanarot | C13: Sushar Manaying | D13: Pavarit Mongkolpisit | E13: Sahajak Boonthanakit | F13: Suthipongse Thatphithakkul | G13: Bhasaworn Bawronkirati | H13: Daweerit Chullasapya | I13: Waratthaya Wongchayaporn | J13: Kittiphoom Wongpentak | K13: Abhicha Thanachanun | L13: Nophand Boonyai | M13: Kittipong Khamsat | N13: Arisara Wongchalee | O13: Jaytiya Naiwattanakul | P13: Pantipa Arunwattanachai | Q13: Panupan Jantanawong | R13: Kungtap Saelim | S13: Phumphat Chartsuriyakiat | T13: Issara Veranitinunt | U13: Keerati Sivakuae | V13: Panjai Sirisuwan | W13: Supranee Charoenpol | X13: Suda Chuenban | Y13: Visaka Banhansupavat | Z13: Pitchatorn Santinatornkul
A14: s13 | B14: Luna Wedler | C14: Jannis NiewÃ¶hner | D14: Milan Peschel | E14: Edin HasanoviÄ‡ | F14: Anna FialovÃ¡ | G14: Marlon Boess | H14: Victor Boccard | I14: Fleur Geffrier | J14: Aziz Dyab | K14: MÃ©lanie FouchÃ© | L14: Elizaveta MaximovÃ¡
A15: s14 | B15: Klara Castanho | C15: Lucca Picon | D15: JÃºlia Gomes | E15: Marcus Bessa | F15: Kiria Malheiros | G15: Fernanda Concon | H15: Gabriel Lima | I15: Caio Cabral | J15: Leonardo Cidade | K15: Jade Cardozo
A16: s15
A17: s16 | B17: Logan Browning | C17: Brandon P. Bell | D17: DeRon Horton | E17: Antoinette Robertson | F17: John Patrick Amedori | G17: Ashley Blaine Featherson | H17: Marque Richardson | I17: Giancarlo Esposito
A18: s17
A19: s18 | B19: Luis Ernesto Franco | C19: Camila Sodi | D19: Sergio Goyri | E19: Samadhi Zendejas | F19: Eduardo YÃ¡Ã±ez | G19: Sonya Smith | H19: Alejandro Camacho | I19: Azela Robinson | J19: Uriel del Toro | K19: GÃ©raldine BazÃ¡n | L19: Gabriela Roel | M19: Marcus Ornellas
A20: s19 | B20: Freida Pinto | C20: Logan Marshall-Green | D20: Robert John Burke | E20: Megan Elisabeth Kelly | F20: Sarah Minnich | G20: Hayes Hargrove | H20: Mark Sivertsen | I20: Brandon Fierro | J20: Antonio Valles | K20: Clint Obenchain
A21: s20 | B21: Blanca SuÃ¡rez | C21: IvÃ¡n Marcos | D21: Ã“scar Casas | E21: AdriÃ¡n Lastra | F21: Francesc Garrido | G21: Stefan Weinert | H21: Julia MÃ¶ller | I21: Alicia Chojnowski
A22: s21
A23: s22 | B23: Engin Altan DÃ¼zyatan | C23: Serdar GÃ¶khan | D23: HÃ¼lya Darcan | E23: Kaan TaÅŸaner | F23: Esra BilgiÃ§ | G23: Osman Soykut | H23: Serdar Deniz | I23: Cengiz CoÅŸkun | J23: Reshad Strik | K23: Hande SubaÅŸÄ±
A24: s23 | B24: Kamal Hassan | C24: Meena | D24: Gemini Ganesan | E24: Heera Rajgopal | F24: Nassar | G24: S.P. Balasubrahmanyam
A25: s24 | B25: Maisie Benson | C25: Paul Killam | D25: Kerry Gudjohnsen | E25: AC Lim
A26: s25 | B26: Prashanth | C26: Aishwarya Rai Bachchan | D26: Sri Lakshmi | E26: Nassar
A27: s26 | B27: Brooke Satchwell
A28: s27 | B28: Arvind Swamy | C28: Kajol | D28: Prabhu Deva | E28: Nassar | F28: S.P. Balasubrahmanyam | G28: Girish Karnad
A29: s28 | B29: Adam Sandler | C29: Kevin James | D29: Chris Rock | E29: David Spade | F29: Rob Schneider | G29: Salma Hayek | H29: Maria Bello | I29: Maya Rudolph | J29: Colin Quinn | K29: Tim Meadows | L29: Joyce Van Patten
A30: s29 | B30: Keri Russell | C30: Josh Hamilton | D30: J.K. Simmons | E30: Dakota Goyo | F30: Kadan Rockett | G30: L.J. Benet | H30: Rich Hutchman | I30: Myndy Crist | J30: Annie Thurman | K30: Jake Brennan
A31: s30 | B31: Liam Hemsworth | C31: Gary Oldman | D31: Amber Heard | E31: Harrison Ford | F31: Lucas Till | G31: Embeth Davidtz | H31: Julian McMahon | I31: Josh Holloway | J31: Richard Dreyfuss | K31: Angela Sarafyan
A32: s31 | B32: Abhishek Banerjee | C32: Rinku Rajguru | D32: Delzad Hiwale | E32: Kunal Kapoor | F32: Zoya Hussain | G32: Nikhil Dwivedi | H32: Palomi Ghosh
A33: s32 | B33: Lauren Ash | C33: Rory O'Malley | D33: RuPaul Charles | E33: Jill Talley | F33: Ike Barinholtz | G33: Jon Barinholtz | H33: Matthew Craig | I33: Bob Odenkirk | J33: Mike Hagerty | K33: Katie Rich | L33: Chris Witaske
A34: s33 | B34: Asa Butterfield | C34: Gillian Anderson | D34: Ncuti Gatwa | E34: Emma Mackey | F34: Connor Swindells | G34: Kedar Williams-Stirling | H34: Alistair Petrie
A35: s34 | B35: Lee Jung-jae | C35: Park Hae-soo | D35: Wi Ha-jun | E35: Oh Young-soo | F35: Jung Ho-yeon | G35: Heo Sung-tae | H35: Kim Joo-ryoung | I35: Tripathi Anupam | J35: You Seong-joo | K35: Lee You-mi
A36: s35 | B36: Dami Lee | C36: Jason Lee | D36: Bommie Catherine Han | E36: Jennifer Waescher | F36: Nancy Kim
A37: s36 | B37: Adrian Titieni | C37: Elena Purea | D37: Judith State | E37: Valeriu AndriuÈ›Äƒ | F37: Tudor Smoleanu | G37: Virgil Aioanei | H37: Radu Botar | I37: Petronela Grigorescu | J37: Bogdan Nechifor | K37: Cristian Bota
A38: s37 | B38: Gilles Lellouche | C38: Karim Leklou | D38: FranÃ§ois Civil | E38: AdÃ¨le Exarchopoulos | F38: Kenza Fortas | G38: Cyril Lecomte | H38: MichaÃ«l Abiteboul | I38: Idir Azougli | J38: Vincent Darmuzey | K38: Jean-Yves Berteloot
A39: s38 | B39: Antti PÃ¤Ã¤kkÃ¶nen | C39: HeljÃ¤ Heikkinen | D39: Lynne Guaglione | E39: Pasi Ruohonen | F39: Rauno Ahonen
A40: s39 | B40: Billy Magnussen | C40: Ron Yuan | D40: Qu Jingjing | E40: Terry Chen | F40: Vanness Wu | G40: Jin Xing | H40: Philip Ng | I40: Xia Yu | J40: Yu Xia
A41: s40 | B41: Vatsal Dubey | C41: Julie Tejwani | D41: Rupa Bhimani | E41: Jigna Bhardwaj | F41: Rajesh Kava | G41: Mousam | H41: Swapnil
A42: s41 | B42: Yuri Lowenthal | C42: Kimberly Brooks | D42: Antony Del Rio | E42: Trevor Devall | F42: Ben Diskin | G42: Grey Griffin | H42: David Kaye | I42: Tom Kenny | J42: Judy Alice Lee | K42: Roger Craig Smith | L42: Fred Tatasciore
A43: s42 | B43: Roy Scheider | C43: Robert Shaw | D43: Richard Dreyfuss | E43: Lorraine Gary | F43: Murray Hamilton | G43: Carl Gottlieb | H43: Jeffrey Kramer | I43: Susan Backlinie | J43: Jonathan Filley | K43: Ted Grossman
A44: s43 | B44: Roy Scheider | C44: Lorraine Gary | D44: Murray Hamilton | E44: Joseph Mascolo | F44: Jeffrey Kramer | G44: Collin Wilcox Paxton | H44: Ann Dusenberry | I44: Mark Gruner | J44: Barry Coe | K44: Susan French
A45: s44 | B45: Dennis Quaid | C45: Bess Armstrong | D45: Simon MacCorkindale | E45: Louis Gossett Jr. | F45: John Putch | G45: Lea Thompson | H45: P.H. Moriarty | I45: Dan Blasko | J45: Liz Morris | K45: Lisa Maurer
A46: s45 | B46: Lorraine Gary | C46: Lance Guest | D46: Mario Van Peebles | E46: Karen Young | F46: Michael Caine | G46: Judith Barsi | H46: Mitchell Anderson | I46: Lynn Whitfield
A47: s46
A48: s47 | B48: Denzel Washington | C48: Ryan Reynolds | D48: Vera Farmiga | E48: Brendan Gleeson | F48: Sam Shepard | G48: RubÃ©n Blades | H48: Nora Arnezeder | I48: Robert Patrick | J48: Liam Cunningham | K48: Joel Kinnaman
A49: s48 | B49: Osas Ighodaro | C49: Ini Dima-Okojie | D49: Kemi Lala Akindoju | E49: Toni Tones | F49: Ebenezer Eno | G49: Eso Okolocha DIke | H49: Patrick Diabuah | I49: Karibi Fubara | J49: Temisan Emmanuel | K49: Timini Egbuson
A50: s49 | B50: Denzel Washington | C50: Ethan Hawke | D50: Scott Glenn | E50: Tom Berenger | F50: Harris Yulin | G50: Raymond J. Barry | H50: Cliff Curtis | I50: Dr. Dre | J50: Snoop Dogg | K50: Macy Gray | L50: Eva Mendes
A51: s50 | B51: Richard Mofe-Damijo | C51: Dakore Akande | D51: Bimbo Manuel | E51: Blossom Chukwujekwu | F51: Deyemi Okanlawon | G51: Etim Effiong | H51: Denola Grey | I51: Duke Akintola | J51: Eku Edewor | K51: Ade Laoye | L51: Anee Icha | M51: Kevin Ushi | N51: Jude Chukwuka | O51: Amanda Afolabi
A52: s51 | B52: Kashmira Irani | C52: Chandan Anand | D52: Dinesh Mehta | E52: Ankit Arora | F52: Pushkar Goggiaa | G52: Anjali Rana | H52: Aarya DharmChand Kumar | I52: Amit Behl | J52: Maleeka Ghai
A53: s52 | B53: Kappei Yamaguchi | C53: Satsuki Yukino | D53: Mieko Harada | E53: Koji Tsujitani | F53: Houko Kuwashima | G53: Kumiko Watanabe | H53: Noriko Hidaka | I53: Kenichi Ogata | J53: Toshiyuki Morikawa | K53: Izumi Ogami
A54: s53 | B54: Kappei Yamaguchi | C54: Satsuki Yukino | D54: Koji Tsujitani | E54: Houko Kuwashima | F54: Kumiko Watanabe | G54: Ken Narita | H54: Akio Otsuka | I54: Kikuko Inoue
A55: s54 | B55: Kappei Yamaguchi | C55: Satsuki Yukino | D55: Koji Tsujitani | E55: Houko Kuwashima | F55: Kumiko Watanabe | G55: Noriko Hidaka | H55: Ken Narita | I55: Cho | J55: Mamiko Noto | K55: Nobutoshi Canna
A56: s55 | B56: Kappei Yamaguchi | C56: Satsuki Yukino | D56: Koji Tsujitani | E56: Houko Kuwashima | F56: Kumiko Watanabe | G56: Kenichi Ogata | H56: Noriko Hidaka | I56: Hisako Kyoda | J56: Ken Narita | K56: Tomokazu Seki
A57: s56 | B57: Nicole Byer | C57: Jacques Torres
A58: s57 | B58: Junko Takeuchi | C58: Chie Nakamura | D58: Rikiya Koyama | E58: Kazuhiko Inoue | F58: Masaki Terasoma | G58: Mie Sonozaki | H58: Yuichi Nakamura | I58: Kengo Kawanishi | J58: Kosei Hirota | K58: Masako Katsuki
A59: s58 | B59: Junko Takeuchi | C59: Chie Nakamura | D59: Noriaki Sugiyama | E59: Unsho Ishizuka | F59: Motoko Kumai | G59: Kazuhiko Inoue | H59: Rikiya Koyama | I59: Showtaro Morikubo | J59: Nana Mizuki | K59: Satoshi Hino | L59: Shinji Kawada
A60: s59 | B60: Junko Takeuchi | C60: Chie Nakamura | D60: Kazuhiko Inoue | E60: Satoshi Hino | F60: Showtaro Morikubo | G60: Kentaro Ito | H60: Ryoka Yuzuki | I60: Kohsuke Toriumi | J60: Nana Mizuki | K60: Shinji Kawada | L60: Yoichi Masukawa | M60: Koichi Tochika | N60: Yukari Tamura
A61: s60 | B61: Junko Takeuchi | C61: Chie Nakamura | D61: Yoichi Masukawa | E61: Koichi Tochika | F61: Ayumi Fujimura | G61: Keisuke Oda | H61: Daisuke Kishio | I61: Fumiko Orikasa | J61: Hidetoshi Nakamura | K61: Tetsuya Kakihara | L61: Kisho Taniyama | M61: Miyuki Sawashiro | N61: Katsuyuki Konishi | O61: Masako Katsuki | P61: Keiko Nemoto | Q61: Masashi Ebara | R61: Kazuhiko Inoue | S61: Showtaro Morikubo | T61: Romi Park | U61: Daisuke Ono | V61: Seizo Kato
A62: s61 | B62: Junko Takeuchi | C62: Chie Nakamura | D62: Satoshi Hino | E62: Rikiya Koyama | F62: Nobuaki Fukuda | G62: Kenji Hamada | H62: Keiko Nemoto | I62: Saori Hayami | J62: Yumi Toma | K62: Yuko Kobayashi | L62: Fujiko Takimoto | M62: Mutsumi Tamura | N62: Mayuki Makiguchi | O62: Toshiyuki Morikawa
A63: s62 | B63: Junko Takeuchi | C63: Gamon Kaai | D63: Chie Nakamura | E63: Showtaro Morikubo | F63: Akira Ishida | G63: Yasuyuki Kase | H63: Urara Takano | I63: Sachiko Kojima | J63: Houko Kuwashima | K63: Takako Honda
A64: s63 | B64: Junko Takeuchi | C64: Chie Nakamura | D64: Yoichi Masukawa | E64: Kazuhiko Inoue | F64: Akio Otsuka | G64: Kyousuke Ikeda | H64: Marika Hayashi | I64: Umeji Sasaki | J64: Masashi Sugawara | K64: Hisao Egawa
A65: s64 | B65: Junko Takeuchi | C65: Noriaki Sugiyama | D65: Chie Nakamura | E65: Kazuhiko Inoue | F65: Yuhko Kaida | G65: Tsutomu Isobe | H65: Hirotaka Suzuoki | I65: Jun Karasawa | J65: Harii Kaneko | K65: Ikuo Nishikawa
A66: s65 | B66: Winslow Fegley | C66: Lidya Jewett | D66: Krysten Ritter
A67: s66 | B67: Beth Chalmers | C67: David Holt | D67: Marcel McCalla | E67: Teresa Gallagher
A68: s67
A69: s68 | B69: Mark-Paul Gosselaar | C69: Tiffani Thiessen | D69: Mario Lopez | E69: Lark Voorhies | F69: Elizabeth Berkley | G69: Dustin Diamond | H69: Dennis Haskins
A70: s69 | B70: Michael Schumacher
A71: s70
A72: s71 | B72: ItatÃ­ Cantoral
A73: s72 | B73: Evan Spiridellis | C73: Erin Fitzgerald | D73: Jeff Gill | E73: Fred Tatasciore | F73: Evan Michael Lee | G73: Jared Isaacman | H73: Sian Proctor | I73: Chris Sembroski | J73: Hayley Arceneaux
A74: s73 | B74: Jack Whitehall | C74: Michael Whitehall
A75: s74 | B75: Sola Sobowale | C75: Adesua Etomi | D75: Remilekun "Reminisce" Safaru | E75: Tobechukwu "iLLbliss" Ejiofor | F75: Toni Tones | G75: Paul Sambo | H75: Jide Kosoko | I75: Sharon Ooja
A76: s75
A77: s76 | B77: Bear Grylls | C77: Jason Derek Prempeh
A78: s77 | B78: Daiki Yamashita | C78: Kohsuke Toriumi | D78: Jun Fukushima | E78: Hiroki Yasumoto | F78: Showtaro Morikubo | G78: Kentaro Ito | H78: Daisuke Kishio | I78: Yoshitsugu Matsuoka | J78: Junichi Suwabe | K78: Ayaka Suwa | L78: Megumi Han | M78: Tomoaki Maeno | N78: Tsubasa Yonaga | O78: Tetsuya Kakihara | P78: Satoshi Hino | Q78: Hiroyuki Yoshino | R78: Atsushi Abe | S78: Koji Yusa | T78: Kouki Miyata | U78: Hiro Shimono | V78: Wataru Hatano | W78: Yuichi Nakamura | X78: Kenji Nojima | Y78: Mamoru Miyano | Z78: Daisuke Ono | AA78: Yuma Uchida | AB78: Jun Fukuyama
A79: s78 | B79: Sumriddhi Shukla | C79: Jigna Bharadwaj | D79: Sonal Kaushal | E79: Neshma Chemburkar | F79: Ganesh Divekar | G79: Annamaya Verma | H79: Anamay Verma | I79: Manoj Pandey
A80: s79 | B80: Vijay Sethupathi | C80: Parthiban | D80: Raashi Khanna
A81: s80 | B81: Vijay Sethupathi | C81: Parthiban | D81: Raashi Khanna
A82: s81 | B82: Thomas Brodie-Sangster | C82: Felicity Jones | D82: Freddie Highmore | E82: Patrick Stewart | F82: Meera Syal | G82: Sanjeev Bhaskar | H82: Nonso Anozie
A83: s82 | B83: Mary Elizabeth Winstead | C83: Jun Kunimura | D83: Woody Harrelson | E83: Tadanobu Asano | F83: Miyavi | G83: Michiel Huisman | H83: Miku Martineau
A84: s83 | B84: Tom Ellis | C84: Lauren German | D84: Kevin Alejandro | E84: D.B. Woodside | F84: Lesley-Ann Brandt | G84: Scarlett Estevez | H84: Rachael Harris | I84: Aimee Garcia | J84: Tricia Helfer | K84: Tom Welling | L84: Jeremiah W. Birkett | M84: Pej Vahdat | N84: Michael Gladis
A85: s84 | B85: Jo Koy
A86: s85 | B86: Funke Akindele | C86: Ayo Makun | D86: Chioma Chukwuka Akpotha | E86: Yemi Eberechi Alade | F86: Blossom Chukwujekwu | G86: Deyemi Okanlawon | H86: Alexx Ekubo | I86: Zubby Michael | J86: Tina Mba | K86: Femi Jacobs
A87: s86 | B87: Ikue Otani | C87: Sarah Natochenny | D87: Zeno Robinson | E87: Cherami Leigh | F87: James Carter Cathcart | G87: Michele Knotz | H87: Rodger Parsons | I87: Ray Chase | J87: Casey Mongillo | K87: Tara Sands
A88: s87 | B88: David Kross | C88: Hanno Koffler | D88: Maria Ehrich | E88: Robert Finster | F88: Yung Ngo | G88: Klaus Steinbacher | H88: Livia Matthes | I88: Nellie Thalbach
A89: s88 | B89: Jeon Hae-ri | C89: Kim Eun-ah | D89: Hong Bum-ki | E89: Nam Do-hyeong | F89: Um Sang-hyun
A90: s89 | B90: Malcolm X | C90: Muhammad Ali
A91: s90 | B91: Julie Tejwani | C91: Sabina Malik | D91: Jigna Bhardwaj | E91: Rupa Bhimani | F91: Lalit Agarwal | G91: Rajesh Shukla | H91: Rajesh Kava
A92: s91 | B92: Emma Roberts | C92: Danielle Macdonald | D92: Awkwafina | E92: Eiza GonzÃ¡lez | F92: Milla Jovovich | G92: Jeremy Irvine | H92: Arnaud Valois | I92: Daniel Horvath
A93: s92
A94: s93 | B94: Pauline Etienne | C94: Laurent Capelluto | D94: Stefano Cassetti | E94: Mehmet KurtuluÅŸ | F94: Babetida Sadjo | G94: Jan Bijvoet | H94: Ksawery Szlenkier | I94: Vincent Londez | J94: Regina Bikkinina | K94: Alba GaÃ¯a Kraghede Bellugi | L94: Nabil Mallat
A95: s94 | B95: Elsa Ã–hrn | C95: Mustapha Aarab | D95: Jonay Pineda Skallak | E95: Magnus Krepper | F95: Loreen | G95: Albin Grenholm | H95: Simon Mezher | I95: Elsa BergstrÃ¶m Terent | J95: Josef Kadim | K95: Yohannes Frezgi
A96: s95 | B96: Will Arnett | C96: Ludacris | D96: Natasha Lyonne | E96: Stanley Tucci | F96: Jordin Sparks | G96: Gabriel Iglesias | H96: Shaquille O'Neal | I96: Omar Chaparro | J96: Alan Cumming | K96: Andy Beckwith | L96: Delia Sheppard | M96: Kerry Shale
A97: s96 | B97: Michelle Buteau
A98: s97 | B98: Ronnie Van Zandt | C98: Gary Rossington | D98: Allen Collins | E98: Leon Wilkeson | F98: Bob Burns | G98: Billy Powell | H98: Ed King | I98: Artimus Pyle | J98: Steve Gaines | K98: Johnny Van Zant
A99: s98 | B99: Jack Fisher | C99: Tom Kenny | D99: Amanda C. Miller | E99: Kim Yarbrough | F99: Keith Ferguson | G99: Grey Griffin | H99: Lily Rose Silver
A100: s99 | B100: Antonio Aakeel | C100: Chipo Chung | D100: Simon Foster | E100: Teresa Gallagher | F100: Simon Greenall | G100: Kate Harbour | H100: Paul Panting | I100: Rob Rackstraw | J100: William Vanderpuye | K100: Helen Walsh | L100: Keith Wickham | M100: Andres Williams | N100: Jo Wyatt
...

Sheet director
A1: show_id | B1: director_1 | C1: director_2 | D1: director_3 | E1: director_4 | F1: director_5 | G1: director_6 | H1: director_7 | I1: director_8 | J1: director_9 | K1: director_10 | L1: director_11 | M1: director_12 | N1: director_13
A2: s1 | B2: Kirsten Johnson
A3: s2
A4: s3 | B4: Julien Leclercq
A5: s4
A6: s5
A7: s6 | B7: Mike Flanagan
A8: s7 | B8: Robert Cullen | C8: JosÃ© Luis Ucha
A9: s8 | B9: Haile Gerima
A10: s9 | B10: Andy Devonshire
A11: s10 | B11: Theodore Melfi
A12: s11
A13: s12 | B13: Kongkiat Komesiri
A14: s13 | B14: Christian Schwochow
A15: s14 | B15: Bruno Garotti
A16: s15
A17: s16
A18: s17 | B18: Pedro de Echave GarcÃ­a | C18: Pablo AzorÃ­n Williams
A19: s18
A20: s19 | B20: Adam Salky
A21: s20
A22: s21 | B22: Olivier Megaton
A23: s22
A24: s23 | B24: K.S. Ravikumar
A25: s24 | B25: Alex Woo | C25: Stanley Moore
A26: s25 | B26: S. Shankar
A27: s26
A28: s27 | B28: Rajiv Menon
A29: s28 | B29: Dennis Dugan
A30: s29 | B30: Scott Stewart
A31: s30 | B31: Robert Luketic
A32: s31 | B32: Ashwiny Iyer Tiwari | C32: Abhishek Chaubey | D32: Saket Chaudhary
A33: s32
A34: s33
A35: s34
A36: s35
A37: s36 | B37: Daniel Sandu
A38: s37 | B38: CÃ©dric Jimenez
A39: s38
A40: s39 | B40: George Nolfi
A41: s40
A42: s41
A43: s42 | B43: Steven Spielberg
A44: s43 | B44: Jeannot Szwarc
A45: s44 | B45: Joe Alves
A46: s45 | B46: Joseph Sargent
A47: s46 | B47: Tyler Greco
A48: s47 | B48: Daniel Espinosa
A49: s48 | B49: Bunmi Ajakaiye
A50: s49 | B50: Antoine Fuqua
A51: s50
A52: s51
A53: s52 | B53: Toshiya Shinohara
A54: s53 | B54: Toshiya Shinohara
A55: s54 | B55: Toshiya Shinohara
A56: s55 | B56: Toshiya Shinohara
A57: s56
A58: s57 | B58: Masahiko Murata
A59: s58 | B59: Hajime Kamegaki
A60: s59 | B60: Masahiko Murata
A61: s60 | B61: Hajime Kamegaki
A62: s61 | B62: Masahiko Murata
A63: s62 | B63: Hirotsugu Kawasaki
A64: s63 | B64: Toshiyuki Tsuru
A65: s64 | B65: Tensai Okamura
A66: s65 | B66: David Yarovesky
A67: s66
A68: s67
A69: s68
A70: s69 | B70: Hanns-Bruno KammertÃ¶ns | C70: Vanessa NÃ¶cker | D70: Michael Wech
A71: s70
A72: s71
A73: s72 | B73: David A. Vargas
A74: s73
A75: s74 | B75: Kemi Adetiba
A76: s75
A77: s76 | B77: Ben Simms
A78: s77
A79: s78 | B79: Prakash Satam
A80: s79 | B80: Delhiprasad Deenadayalan
A81: s80 | B81: Delhiprasad Deenadayalan
A82: s81 | B82: Tomer Eshed
A83: s82 | B83: Cedric Nicolas-Troyan
A84: s83
A85: s84
A86: s85 | B86: JJC Skillz | C86: Funke Akindele
A87: s86
A88: s87 | B88: Thomas Sieben
A89: s88
A90: s89 | B90: Marcus Clarke
A91: s90
A92: s91 | B92: Alice Waddington
A93: s92 | B93: Mona Achache | C93: Patricia Tourancheau
A94: s93
A95: s94 | B95: Alexis AlmstrÃ¶m
A96: s95 | B96: Raja Gosnell
A97: s96
A98: s97 | B98: Stephen Kijak
A99: s98
A100: s99
...

Sheet listed in
A1: show_id | B1: listed_in_1 | C1: listed_in_2 | D1: listed_in_3
A2: s1 | B2: Documentaries
A3: s2 | B3: International TV Shows | C3: TV Dramas | D3: TV Mysteries
A4: s3 | B4: Crime TV Shows | C4: International TV Shows | D4: TV Action & Adventure
A5: s4 | B5: Docuseries | C5: Reality TV
A6: s5 | B6: International TV Shows | C6: Romantic TV Shows | D6: TV Comedies
A7: s6 | B7: TV Dramas | C7: TV Horror | D7: TV Mysteries
A8: s7 | B8: Children & Family Movies
A9: s8 | B9: Dramas | C9: Independent Movies | D9: International Movies
A10: s9 | B10: British TV Shows | C10: Reality TV
A11: s10 | B11: Comedies | C11: Dramas
A12: s11 | B12: Crime TV Shows | C12: Docuseries | D12: International TV Shows
A13: s12 | B13: Crime TV Shows | C13: International TV Shows | D13: TV Action & Adventure
A14: s13 | B14: Dramas | C14: International Movies
A15: s14 | B15: Children & Family Movies | C15: Comedies
A16: s15 | B16: British TV Shows | C16: Crime TV Shows | D16: Docuseries
A17: s16 | B17: TV Comedies | C17: TV Dramas
A18: s17 | B18: Documentaries | C18: International Movies
A19: s18 | B19: Crime TV Shows | C19: Spanish-Language TV Shows | D19: TV Dramas
A20: s19 | B20: Thrillers
A21: s20 | B21: International TV Shows | C21: Spanish-Language TV Shows | D21: TV Action & Adventure
A22: s21 | B22: Crime TV Shows | C22: Docuseries | D22: International TV Shows
A23: s22 | B23: International TV Shows | C23: TV Action & Adventure | D23: TV Dramas
A24: s23 | B24: Comedies | C24: International Movies
A25: s24 | B25: Children & Family Movies
A26: s25 | B26: Comedies | C26: International Movies | D26: Romantic Movies
A27: s26 | B27: Docuseries | C27: International TV Shows | D27: Reality TV
A28: s27 | B28: Comedies | C28: International Movies | D28: Music & Musicals
A29: s28 | B29: Comedies
A30: s29 | B30: Horror Movies | C30: Sci-Fi & Fantasy
A31: s30 | B31: Thrillers
A32: s31 | B32: Dramas | C32: Independent Movies | D32: International Movies
A33: s32 | B33: TV Comedies
A34: s33 | B34: British TV Shows | C34: International TV Shows | D34: TV Comedies
A35: s34 | B35: International TV Shows | C35: TV Dramas | D35: TV Thrillers
A36: s35 | B36: Kids' TV
A37: s36 | B37: Dramas | C37: International Movies | D37: Thrillers
A38: s37 | B38: Action & Adventure | C38: Dramas | D38: International Movies
A39: s38 | B39: Kids' TV | C39: TV Comedies
A40: s39 | B40: Action & Adventure | C40: Dramas
A41: s40 | B41: Kids' TV
A42: s41 | B42: Kids' TV | C42: TV Sci-Fi & Fantasy
A43: s42 | B43: Action & Adventure | C43: Classic Movies | D43: Dramas
A44: s43 | B44: Dramas | C44: Horror Movies | D44: Thrillers
A45: s44 | B45: Action & Adventure | C45: Horror Movies | D45: Thrillers
A46: s45 | B46: Action & Adventure | C46: Horror Movies | D46: Thrillers
A47: s46 | B47: Documentaries
A48: s47 | B48: Action & Adventure
A49: s48 | B49: International TV Shows | C49: Romantic TV Shows | D49: TV Comedies
A50: s49 | B50: Dramas | C50: Thrillers
A51: s50 | B51: International TV Shows | C51: TV Dramas
A52: s51 | B52: International TV Shows | C52: TV Dramas | D52: TV Sci-Fi & Fantasy
A53: s52 | B53: Action & Adventure | C53: Anime Features | D53: International Movies
A54: s53 | B54: Action & Adventure | C54: Anime Features | D54: International Movies
A55: s54 | B55: Action & Adventure | C55: Anime Features | D55: International Movies
A56: s55 | B56: Action & Adventure | C56: Anime Features | D56: International Movies
A57: s56 | B57: Reality TV
A58: s57 | B58: Action & Adventure | C58: Anime Features | D58: International Movies
A59: s58 | B59: Action & Adventure | C59: Anime Features | D59: International Movies
A60: s59 | B60: Action & Adventure | C60: Anime Features | D60: International Movies
A61: s60 | B61: Action & Adventure | C61: Anime Features | D61: International Movies
A62: s61 | B62: Action & Adventure | C62: Anime Features | D62: International Movies
A63: s62 | B63: Action & Adventure | C63: Anime Features | D63: International Movies
A64: s63 | B64: Action & Adventure | C64: Anime Features | D64: International Movies
A65: s64 | B65: Action & Adventure | C65: Anime Features | D65: International Movies
A66: s65 | B66: Children & Family Movies
A67: s66 | B67: Kids' TV
A68: s67 | B68: Docuseries | C68: International TV Shows
A69: s68 | B69: Kids' TV | C69: TV Comedies
A70: s69 | B70: Documentaries | C70: International Movies | D70: Sports Movies
A71: s70 | B71: International TV Shows | C71: TV Dramas
A72: s71 | B72: International TV Shows | C72: Reality TV | D72: Romantic TV Shows
A73: s72 | B73: Children & Family Movies
A74: s73 | B74: British TV Shows | C74: Docuseries | D74: International TV Shows
A75: s74 | B75: Dramas | C75: International Movies
A76: s75 | B76: Reality TV
A77: s76 | B77: Children & Family Movies
A78: s77 | B78: Anime Series | C78: International TV Shows
A79: s78 | B79: Children & Family Movies | C79: Comedies
A80: s79 | B80: Comedies | C80: Dramas | D80: International Movies
A81: s80 | B81: Comedies | C81: Dramas | D81: International Movies
A82: s81 | B82: Children & Family Movies
A83: s82 | B83: Action & Adventure
A84: s83 | B84: Crime TV Shows | C84: TV Comedies | D84: TV Dramas
A85: s84 | B85: Reality TV
A86: s85 | B86: Action & Adventure | C86: Comedies | D86: Dramas
A87: s86 | B87: Anime Series | C87: Kids' TV
A88: s87 | B88: International Movies | C88: Thrillers
A89: s88 | B89: Kids' TV | C89: Korean TV Shows
A90: s89 | B90: Documentaries | C90: Sports Movies
A91: s90 | B91: Kids' TV
A92: s91 | B92: Sci-Fi & Fantasy | C92: Thrillers
A93: s92 | B93: Documentaries | C93: International Movies
A94: s93 | B94: International TV Shows | C94: TV Dramas | D94: TV Mysteries
A95: s94 | B95: Dramas | C95: International Movies | D95: Romantic Movies
A96: s95 | B96: Children & Family Movies | C96: Comedies
A97: s96 | B97: Reality TV
A98: s97 | B98: Documentaries | C98: Music & Musicals
A99: s98 | B99: Kids' TV | C99: TV Comedies | D99: TV Sci-Fi & Fantasy
A100: s99 | B100: British TV Shows | C100: Kids' TV
...

Sheet country
A1: show_id | B1: country_1 | C1: country_2 | D1: country_3 | E1: country_4 | F1: country_5 | G1: country_6 | H1: country_7 | I1: country_8 | J1: country_9 | K1: country_10 | L1: country_11 | M1: country_12
A2: s1 | B2: United States
A3: s2 | B3: South Africa
A4: s3
A5: s4
A6: s5 | B6: India
A7: s6
A8: s7
A9: s8 | B9: United States | C9: Ghana | D9: Burkina Faso | E9: United Kingdom | F9: Germany | G9: Ethiopia
A10: s9 | B10: United Kingdom
A11: s10 | B11: United States
A12: s11
A13: s12
A14: s13 | B14: Germany | C14: Czech Republic
A15: s14
A16: s15
A17: s16 | B17: United States
A18: s17
A19: s18 | B19: Mexico
A20: s19
A21: s20
A22: s21
A23: s22 | B23: Turkey
A24: s23
A25: s24
A26: s25 | B26: India
A27: s26 | B27: Australia
A28: s27
A29: s28 | B29: United States
A30: s29 | B30: United States
A31: s30 | B31: United States | C31: India | D31: France
A32: s31
A33: s32
A34: s33 | B34: United Kingdom
A35: s34
A36: s35
A37: s36
A38: s37
A39: s38 | B39: Finland
A40: s39 | B40: China | C40: Canada | D40: United States
A41: s40 | B41: India
A42: s41 | B42: United States
A43: s42 | B43: United States
A44: s43 | B44: United States
A45: s44 | B45: United States
A46: s45 | B46: United States
A47: s46
A48: s47 | B48: South Africa | C48: United States | D48: Japan
A49: s48
A50: s49 | B50: United States
A51: s50 | B51: Nigeria
A52: s51 | B52: India
A53: s52 | B53: Japan
A54: s53 | B54: Japan
A55: s54 | B55: Japan
A56: s55 | B56: Japan
A57: s56 | B57: United States
A58: s57 | B58: Japan
A59: s58 | B59: Japan
A60: s59 | B60: Japan
A61: s60 | B61: Japan
... A65: s64 | B65: Japan
A66: s65
A67: s66 | B67: United Kingdom
A68: s67 | B68: India
A69: s68 | B69: United States
A70: s69
A71: s70 | B71: India
A72: s71
A73: s72
A74: s73 | B74: United Kingdom
A75: s74 | B75: Nigeria
A76: s75
A77: s76
A78: s77 | B78: Japan
A79: s78
A80: s79
A81: s80
A82: s81
A83: s82 | B83: United States
A84: s83 | B84: United States
A85: s84
A86: s85 | B86: Nigeria
A87: s86
A88: s87
A89: s88
A90: s89
A91: s90
A92: s91 | B92: Spain | C92: United States
A93: s92 | B93: France
A94: s93 | B94: Belgium
A95: s94
A96: s95 | B96: United Kingdom | C96: United States
A97: s96 | B97: United States | C97: United Kingdom
A98: s97 | B98: United States
A99: s98 | B99: United States
A100: s99 | B100: United Kingdom
A101: s100 | B101: France | C101: United States
A102: s101
A103: s102 | B103: United States
...

Sheet description
A1: show_id | B1: description
A2: s1 | B2: As her father nears the end of his life, filmmaker Kirsten Johnson stages his death in inventive and comical ways to help them both face the inevitable.
A3: s2 | B3: After crossing paths at a party, a Cape Town teen sets out to prove whether a private-school swimming star is her sister who was abducted at birth.
A4: s3 | B4: To protect his family from a powerful drug lord, skilled thief Mehdi and his expert team of robbers are pulled into a violent and deadly turf war.
A5: s4 | B5: Feuds, flirtations and toilet talk go down among the incarcerated women at the Orleans Justice Center in New Orleans on this gritty reality series.
A6: s5 | B6: In a city of coaching centers known to train Indiaâ€™s finest collegiate minds, an earnest but unexceptional student and his friends navigate campus life.
A7: s6 | B7: The arrival of a charismatic young priest brings glorious miracles, ominous mysteries and renewed religious fervor to a dying town desperate to believe.
A8: s7 | B8: Equestria's divided. But a bright-eyed hero believes Earth Ponies, Pegasi and Unicorns should be pals â€” and, hoof to heart, sheâ€™s determined to prove it.
A9: s8 | B9: On a photo shoot in Ghana, an American model slips back in time, becomes enslaved on a plantation and bears witness to the agony of her ancestral past.
A10: s9 | B10: A talented batch of amateur bakers face off in a 10-week competition, whipping up their best dishes in the hopes of being named the U.K.'s best.
A11: s10 | B11: A woman adjusting to life after a loss contends with a feisty bird that's taken over her garden â€” and a husband who's struggling to find a way forward.
A12: s11 | B12: Sicily boasts a bold "Anti-Mafia" coalition. But what happens when those trying to bring down organized crime are accused of being criminals themselves?
... A8808: s8807 | B8808: A scrappy but poor boy worms his way into a tycoon's dysfunctional family, while facing his fear of music and the truth about his past.
